metabolike/__init__.py
metabolike/config.py
metabolike/main.py
metabolike/utils.py
metabolike/algo/__init__.py
metabolike/algo/compounds.py
metabolike/algo/omics.py
metabolike/algo/routes.py
metabolike/api/__init__.py
metabolike/api/data.py
metabolike/api/main.py
metabolike/db/__init__.py
metabolike/db/metacyc.py
metabolike/db/neo4j.py
metabolike/db/sbml.py
metabolike/parser/__init__.py
metabolike/parser/bkms_react.py
metabolike/parser/brenda.py
metabolike/parser/brenda_transformer.py
metabolike/parser/metacyc.py
metabolike/parser/sbml.py
metabolike-0.5.0.dist-info/entry_points.txt
metabolike-0.5.0.dist-info/LICENSE
metabolike-0.5.0.dist-info/WHEEL
metabolike-0.5.0.dist-info/METADATA
metabolike-0.5.0.dist-info/RECORD
