Metadata-Version: 2.1
Name: metabolike
Version: 0.5.0
Summary: Build graph database from BRENDA and BioCyc for studying reprogrammed metabolisms.
Keywords: bioinformatics,metabolic-pathway,network,graph-database
Author-email: Yi Zhou <metabolike@y1zhou.com>
Requires-Python: >=3.8,<4
Classifier: License :: OSI Approved :: GNU General Public License v3 or later (GPLv3+)
Classifier: Development Status :: 2 - Pre-Alpha
Classifier: Programming Language :: Python :: 3
Classifier: Framework :: FastAPI
Classifier: Framework :: Pytest
Classifier: Framework :: Sphinx
Classifier: Intended Audience :: Science/Research
Classifier: Topic :: Scientific/Engineering :: Bio-Informatics
Classifier: Typing :: Typed
Requires-Dist: lark>=0.11.3,<2.0.0
Requires-Dist: pandas>=1.0.0,<2.0.0
Requires-Dist: orjson>=3.6.2,<4.0.0
Requires-Dist: numpy>=1.22.0,<2.0.0
Requires-Dist: python-libsbml>=5.19.2
Requires-Dist: neo4j>=5.0.0
Requires-Dist: tqdm>=4.64.0
Requires-Dist: pyyaml>=6.0.0
Requires-Dist: typer>=0.4.1,<0.5.0
Requires-Dist: fastapi>=0.71.0,<0.76.0
Requires-Dist: uvicorn>=0.17.0,<0.18.0
Requires-Dist: requests>=2.28.0
Requires-Dist: rdkit>=2022.3.3
Requires-Dist: black>=22.3.0 ; extra == "dev"
Requires-Dist: sphinx ; extra == "doc"
Requires-Dist: sphinx_rtd_theme ; extra == "doc"
Requires-Dist: sphinx-autodoc-typehints ; extra == "doc"
Requires-Dist: pytest ; extra == "test"
Requires-Dist: pytest-cov ; extra == "test"
Requires-Dist: pytest-mock ; extra == "test"
Requires-Dist: coverage<6.4 ; extra == "test"
Requires-Dist: coverage[toml]<6.4 ; extra == "test"
Requires-Dist: hypothesis>=6.47.0 ; extra == "test"
Requires-Dist: pytest-dotenv>=0.5.2 ; extra == "test"
Project-URL: Documentation, https://metabolike.readthedocs.io/
Project-URL: Source, https://github.com/y1zhou/metabolike
Provides-Extra: dev
Provides-Extra: doc
Provides-Extra: test
